openmind/__init__.py
openmind/metrics.py
openmind/omdatasets.py
openmind/public_address_lib.json
openmind/trainers.py
openmind/version.py
openmind/archived/__init__.py
openmind/archived/models/__init__.py
openmind/archived/models/auto/__init__.py
openmind/archived/models/auto/auto_factory.py
openmind/archived/models/auto/auto_ms.py
openmind/archived/models/auto/auto_pt.py
openmind/archived/pipelines/__init__.py
openmind/archived/pipelines/base.py
openmind/archived/pipelines/builder.py
openmind/archived/pipelines/interface.py
openmind/archived/pipelines/native_pipelines.json
openmind/archived/pipelines/pipeline_utils.py
openmind/archived/pipelines/common/__init__.py
openmind/archived/pipelines/common/hf.py
openmind/archived/pipelines/common/hf_utils.py
openmind/archived/pipelines/common/ms.py
openmind/archived/pipelines/common/ms_utils.py
openmind/archived/pipelines/common/util.py
openmind/archived/trainers/__init__.py
openmind/archived/trainers/pretrainer.py
openmind/archived/trainers/pretrainer_utils.py
openmind/archived/trainers/pretraining_args.py
openmind/archived/trainers/trainer.py
openmind/archived/trainers/trainer_utils.py
openmind/archived/trainers/training_args.py
openmind/cli/__init__.py
openmind/cli/cli_docker.py
openmind/cli/cli_utils.py
openmind/cli/env.py
openmind/cli/export.py
openmind/cli/list.py
openmind/cli/lmeval.py
openmind/cli/openmind_cli.py
openmind/cli/pull.py
openmind/cli/push.py
openmind/cli/rm.py
openmind/cli/run.py
openmind/cli/subcommand.py
openmind/cli/chat/__init__.py
openmind/cli/chat/chat.py
openmind/cli/chat/chat_engine.py
openmind/cli/chat/chat_model.py
openmind/cli/chat/chat_utils.py
openmind/cli/chat/data/__init__.py
openmind/cli/chat/data/data_utils.py
openmind/cli/chat/data/formatter.py
openmind/cli/chat/data/hparams.py
openmind/cli/chat/data/template.py
openmind/cli/chat/data/tool_utils.py
openmind/cli/chat/model/__init__.py
openmind/cli/chat/model/adapter.py
openmind/cli/chat/model/attention.py
openmind-1.0.0.dist-info/METADATA
openmind-1.0.0.dist-info/WHEEL
openmind-1.0.0.dist-info/entry_points.txt
openmind-1.0.0.dist-info/licenses/LICENSE
openmind-1.0.0.dist-info/licenses/LICENSE-Apache-2.0
openmind-1.0.0.dist-info/RECORD
