Metadata-Version: 2.4
Name: openmind
Version: 1.0.0
Summary: openMind is a magicain who takes you to experience the mystery and creativity of AI.
Project-URL: Homepage, https://gitee.com/openmind-ai/openmind
Project-URL: Repository, https://gitee.com/openmind-ai/openmind
Author: The openMind Team
Author-email: dev@public.openmind.cn
License: 木兰宽松许可证， 第2版
License-File: LICENSE
License-File: LICENSE-Apache-2.0
Classifier: Development Status :: 1 - Planning
Classifier: Intended Audience :: Developers
Classifier: Intended Audience :: Education
Classifier: Intended Audience :: Science/Research
Classifier: License :: OSI Approved :: Mulan Permissive Software License v2 (MulanPSL-2.0)
Classifier: Operating System :: OS Independent
Classifier: Programming Language :: Python :: 3
Classifier: Programming Language :: Python :: 3.8
Classifier: Programming Language :: Python :: 3.9
Classifier: Programming Language :: Python :: 3.10
Classifier: Topic :: Scientific/Engineering :: Artificial Intelligence
Requires-Python: <3.11,>=3.8
Requires-Dist: datasets<=2.21.0,>=2.18.0
Requires-Dist: decorator
Requires-Dist: docker>=4.34.2
Requires-Dist: einops==0.8.0
Requires-Dist: numpy<2.0.0
Requires-Dist: openmind-hub==0.9.1
Requires-Dist: packaging
Requires-Dist: sentencepiece
Requires-Dist: setuptools==69.5.1
Requires-Dist: tabulate
Requires-Dist: tiktoken
Requires-Dist: tokenizers
Requires-Dist: tqdm
Provides-Extra: ci
Requires-Dist: requests; extra == 'ci'
Provides-Extra: lint
Requires-Dist: black==24.8.0; extra == 'lint'
Requires-Dist: ruff==0.6.1; extra == 'lint'
Provides-Extra: ms
Requires-Dist: mindformers==1.3.0; extra == 'ms'
Requires-Dist: mindspore==2.4.0; extra == 'ms'
Provides-Extra: pt
Requires-Dist: accelerate<=1.0.0rc1,>=0.28.0; extra == 'pt'
Requires-Dist: deepspeed<=0.15.4,>=0.12.6; extra == 'pt'
Requires-Dist: diffusers<=0.31.0,>=0.29.0; extra == 'pt'
Requires-Dist: evaluate==0.4.1; extra == 'pt'
Requires-Dist: lm-eval==0.4.3; extra == 'pt'
Requires-Dist: peft<=0.14.0,>=0.12.0; extra == 'pt'
Requires-Dist: torch-npu==2.1.0.post8; extra == 'pt'
Requires-Dist: torch==2.1.0; extra == 'pt'
Requires-Dist: transformers<=4.45.2,>=4.39.2; extra == 'pt'
Provides-Extra: pt-cpu
Requires-Dist: accelerate<=1.0.0rc1,>=0.28.0; extra == 'pt-cpu'
Requires-Dist: deepspeed<=0.15.4,>=0.12.6; extra == 'pt-cpu'
Requires-Dist: diffusers<=0.31.0,>=0.29.0; extra == 'pt-cpu'
Requires-Dist: evaluate==0.4.1; extra == 'pt-cpu'
Requires-Dist: lm-eval==0.4.3; extra == 'pt-cpu'
Requires-Dist: peft<=0.14.0,>=0.12.0; extra == 'pt-cpu'
Requires-Dist: torch==2.1.0; extra == 'pt-cpu'
Requires-Dist: transformers<=4.45.2,>=4.39.2; extra == 'pt-cpu'
Provides-Extra: test
Requires-Dist: accelerate<=1.0.0rc1,>=0.28.0; extra == 'test'
Requires-Dist: deepspeed<=0.15.4,>=0.12.6; extra == 'test'
Requires-Dist: diffusers<=0.31.0,>=0.29.0; extra == 'test'
Requires-Dist: evaluate==0.4.1; extra == 'test'
Requires-Dist: lm-eval==0.4.3; extra == 'test'
Requires-Dist: peft<=0.14.0,>=0.12.0; extra == 'test'
Requires-Dist: pillow; extra == 'test'
Requires-Dist: pytest; extra == 'test'
Requires-Dist: pytest-cov; extra == 'test'
Requires-Dist: testtools; extra == 'test'
Requires-Dist: torch==2.1.0; extra == 'test'
Requires-Dist: transformers<=4.45.2,>=4.39.2; extra == 'test'
